unequalpy/__init__.py
unequalpy/approximation.py
unequalpy/lens_filter.py
unequalpy/matter.py
unequalpy-0.1.3.dist-info/LICENSE.txt
unequalpy-0.1.3.dist-info/METADATA
unequalpy-0.1.3.dist-info/WHEEL
unequalpy-0.1.3.dist-info/top_level.txt
unequalpy-0.1.3.dist-info/RECORD
