Metadata-Version: 2.1
Name: unequalpy
Version: 0.1.3
Summary: unequal-time power spectrum functions
Home-page: https://github.com/Lucia-Fonseca/unequalpy.git
Author: Lucia Fonseca de la Bella
Author-email: lucia.fonsecadelabella@manchester.ac.uk
License: MIT
Platform: UNKNOWN
Classifier: Programming Language :: Python :: 3
Classifier: License :: OSI Approved :: MIT License
Classifier: Operating System :: OS Independent
Requires-Python: >=3.6
License-File: LICENSE.txt
Requires-Dist: astropy
Requires-Dist: corfu (==0.1.1)
Requires-Dist: numpy
Requires-Dist: scipy
Requires-Dist: tqdm
Provides-Extra: docs
Requires-Dist: sphinxcontrib.bibtex ; extra == 'docs'
